{
  "solargraph.formatting": true,
  "languageserver": {
    "efm": {
      "command": "efm-langserver",
      "args": [],
      "filetypes": [
        "vim",
        "markdown",
        "text",
        "html",
        "javascript", "typescript", "vue",
        "css", "scss", "sass",
        "json",
        "yaml",
        "ruby",
        "c", "cpp",
        "sh", "zsh"
      ]
    },
    "terraform": {
      "command": "terraform-lsp",
      "filetypes": [
        "terraform"
      ],
      "initializationOptions": {},
      "settings": {}
    }
  }
}
